[
  {
    "image": "/previews/data-preview-1.png",
    "image_alt": "A Map",
    "title": "Future precipitation map",
    "blurb": "<a href=\"\">Access a <a href=\"#\">web map service</a> combining projected CMIP5 precipitation and USGS web map services. This can be used in GIS programs to produce data summaries at a local scale.</a>",
    "tags": ["Precipitation", "WMS", "Visualization", "GIS"]
  },
  {
    "image": null,
    "image_alt": null,
    "title": "ALFRESCO flammability and vegetation",
    "blurb": "Access flammability and predominant vegetation type for a latitude/longitude point or area of interest in JSON or CSV format with <a href=\"https://earthmaps.io/alfresco/\">this API endpoint</a>.",
    "tags": ["Wildfire", "Vegetation", "API"]
  }
]
